LICENSE.txt
README.md
setup.cfg
setup.py
noun_splitter.egg-info/PKG-INFO
noun_splitter.egg-info/SOURCES.txt
noun_splitter.egg-info/dependency_links.txt
noun_splitter.egg-info/requires.txt
noun_splitter.egg-info/top_level.txt
secos/Decomposition.py
secos/__init__.py
secos/__main__.py
secos/models/__init__.py
secos/models/download.py
secos/models/load.py
secos/models/models.py
secos/utils/__init__.py
secos/utils/utils.py