Metadata-Version: 2.1
Name: noun-splitter
Version: 0.0.1
Summary: Python module to decompose nouns based on the SECOS algorithm
Home-page: https://github.com/mhaugestad/noun-splitter
Download-URL: https://github.com/mhaugestad/noun-splitter/archive/refs/tags/0.0.1.tar.gz
Author: Mathias Haugestad
Author-email: mhaugestad@gmail.com
Requires-Python: >=3.6
License-File: LICENSE.txt
